{"image":{"image_id":37,"license":1,"file_name":"image_405_jpeg.rf.CDegQwXt9MLGVyEFXwW7.jpeg","height":512,"width":512,"date_captured":"2026-04-09T04:50:40+00:00","extra":{"name":"image_405.jpeg"}},"annotations":[{"id":37,"bbox":[89,141,353,255],"area":90015,"segmentation":{"counts":"lk\\1<a?6K3L3N2N2N2O1O1O1N2O1N101N2N2N2N1N3N1FbNRB`1l=:0000010O01O100O1O1O1O1@nMQCS2m<QNPCP2o<QNPCP2o<RNoBo1Q=RNmBo1R=SNkBo1T=>1000O1O100O010O1O010O1O00100O100O2O0O1O100O100O10O01000OUL[M\\Jf2c5aMWJ_2i5eMVGA]2i2^6ZN]Ig1c6[N[Id1f6_NWIa1h6aNVI`1i6cNUI\\1j6iNSIW1k6mNSIR1l6SOQIm0n6WOnHj0P7ZOnHe0R7^OlHb0S7AkH>V7DgH=X7FfH:Z7HdH7\\7KbH6]7LbH4^7MaH2_70`HOa73]HMc74\\HKd78ZHHf7;WHDj7`0RH@n7a0QH^Oo7e0oG[OQ8f0nGYOS8h0lGXOT8i0ZG_L9g2^8S1aGmN_8T1`GkNa8U1_GkNa8V1^GjNb8V1^GiNc8W1]GiNc8W1]GiNc8W1]GiNc8X1\\GhNd8X1]GgNd8X1\\GhNd8X1\\GgNe8Y1[GgNf8Y1YGgNh8Y1WGfNj8Z1WGeNi8\\1VGdNk8\\1TGcNn8\\1RGdNn8]1RGbNo8]1QGbNQ9^1nFbNS9]1nFaNT9^1lFbNU9]1lFaNV9^1jFaNX9^1hFbNY9]1hFaNZ9^1fFaN\\9^1dFbN^9\\1bFcN`9\\1`FdNa9[1^FeNe9Y1[FgNf9X1YFiNj9TNWF[2LBP:oM\\FY2CIm:5RELo:>REUOP;h0SEVOn:h0UEVOm:h0UEVOn:h0SEVOP;g0REVOR;g0PEWOR;g0PEWOR;g0PEVOS;h0oDVOT;h0mDUOV;i0kDUOX;i0jDTOX;l0cDWO`;g0[D]Oh;b0TD^OQ<b0jCmNLF\\<^2gC]M[<b2lCUMX<j2?O20O4M7H3N0O01O1O000O01000O1100O100000001O0002N1O1O00O100O1O1N101O001NWMaCS2Z<_MbC=7R2U<UNkCk1R<jMiCN6V2P<[NQDe1n;\\NRDc1m;^NTDb1j;`NUDa1i;aNWD_1g;cNYD]1e;dN\\D]1a;eN_DQOFQ2j;oNaDkNKU2a;ROdDgNNW2\\;ROREn0l:TOUEl0i:UOWEl0f:VOZEj0e:XOZEi0d:YO\\Ef0b:]O]Ed0a:^O^Ec0`:_O_Ea0`:A_E`0_:B`E?^:CaE=^:EaE<]:EcE<[:FdE:[:HeE8Z:IeE7Z:KeE6Y:KgE5Y:LfE5Y:KgE6X:KgE5Y:KgE6X:KgE5Z:JfE7Y:JfE6[:IfEeMJ[2_:1nENR:2oENP:2QFMn95QFLn94SFKm95TFKj97VFHj98VFIi97WFIh99XFGg9:YFEf9<ZFEe9<[FCd9>\\FBd9>]FBb9>_FAa9?_FA`9`0`FA_9?aFA_9?aFA^9`0bFA]9?cFA\\9`0dF@\\9`0dFAZ9`0fF@Z9`0fF@Y9a0gF@X9a0hF^OX9b0hF^OW9c0iF]OW9c0jF]OU9c0kF]OT9d0mF[OS9f0lF[OS9e0nFZOR9f0nFZOS9e0nF[OQ9e0PGZOP9f0QGYOo8g0QGZOn8f0SGYOm8f0UGZOi8g0XGXOh8h0XGYOg8f0[GYOd8h0]GXOb8h0_GfMTOc0]9f1`GfMWOa0X9j1cGcMXOa0T9k1fGbMYOa0Q9m1gG`M[Oa0m8P2iG]M]Ob0i8Q2kG[M^Oc0g8Q2mGZM_Oc0c8T2PHUMBd0^8W2[IeMe6[2^IbMb6^2`I`M_6a2cI]M]6b2fI\\MZ6d2hIZMW6g2lIUMU6k2`3O01000O01000O10O10O1O100O100O100O1O10001N2O1N101N101N1O2N1EbBSN`=k1cBRN`=O`Bc1U>N1O1O1O00100O1O1O001O100O1O1N2O2M2O2M3N2CPAFS?6RAFQ?7`0ITjR1","size":[512,512]}}]}